lightningrobot_plugin_echo/__init__.py
lightningrobot_plugin_echo-0.1.5.dist-info/LICENSE
lightningrobot_plugin_echo-0.1.5.dist-info/METADATA
lightningrobot_plugin_echo-0.1.5.dist-info/WHEEL
lightningrobot_plugin_echo-0.1.5.dist-info/RECORD
