Metadata-Version: 2.1
Name: lightningrobot-plugin-echo
Version: 0.1.5
Summary: 闪电机器人复读机插件。
Author: Zhihan
Author-email: zhihan2727@hotmail.com
Requires-Python: >=3.11,<4.0
Classifier: Programming Language :: Python :: 3
Classifier: Programming Language :: Python :: 3.11
Requires-Dist: lightningrobot (>=1.0.0,<2.0.0)
